mlflow_oidc_auth_groups_plugin_adfs-0.0.1.dist-info/METADATA
mlflow_oidc_auth_groups_plugin_adfs-0.0.1.dist-info/WHEEL
mlflow_oidc_auth_groups_plugin_adfs-0.0.1.dist-info/entry_points.txt
mlflow_oidc_auth_groups_plugin_adfs-0.0.1.dist-info/licenses/LICENSE
mlflow_oidc_auth_groups_plugin_adfs/__init__.py
mlflow_oidc_auth_groups_plugin_adfs/groups.py
mlflow_oidc_auth_groups_plugin_adfs-0.0.1.dist-info/RECORD
