Metadata-Version: 2.4
Name: mlflow-oidc-auth-groups-plugin-adfs
Version: 0.0.1
Summary: ADFS groups plugin for mlflow-oidc-auth
Author-Email: Artur <arturauth@proton.me>
License-Expression: MIT
License-File: LICENSE
Classifier: Development Status :: 4 - Beta
Classifier: Intended Audience :: Developers
Classifier: Programming Language :: Python
Classifier: Programming Language :: Python :: 3
Classifier: Programming Language :: Python :: 3 :: Only
Classifier: Programming Language :: Python :: 3.9
Classifier: Programming Language :: Python :: 3.10
Classifier: Programming Language :: Python :: 3.11
Classifier: Programming Language :: Python :: 3.12
Classifier: Programming Language :: Python :: 3.13
Classifier: Programming Language :: Python :: 3.14
Classifier: Topic :: Scientific/Engineering :: Artificial Intelligence
Classifier: Topic :: Software Development :: Libraries :: Python Modules
Classifier: Typing :: Typed
Project-URL: Homepage, https://arturauth.github.io/mlflow-oidc-auth-groups-plugin-adfs
Project-URL: Documentation, https://arturauth.github.io/mlflow-oidc-auth-groups-plugin-adfs
Project-URL: Changelog, https://arturauth.github.io/mlflow-oidc-auth-groups-plugin-adfs/changelog
Project-URL: Repository, https://github.com/arturauth/mlflow-oidc-auth-groups-plugin-adfs
Project-URL: Issues, https://github.com/arturauth/mlflow-oidc-auth-groups-plugin-adfs/issues
Project-URL: Discussions, https://github.com/arturauth/mlflow-oidc-auth-groups-plugin-adfs/discussions
Project-URL: Gitter, https://gitter.im/mlflow-oidc-auth-groups-plugin-adfs/community
Project-URL: Funding, https://github.com/sponsors/arturauth
Requires-Python: >=3.9
